MANIFEST.in
README.md
eicar.com
setup.py
eicar_pack_10/__init__.py
eicar_pack_10/eic_py_.py
eicar_pack_10/eicar.com
mik_py.egg-info/PKG-INFO
mik_py.egg-info/SOURCES.txt
mik_py.egg-info/dependency_links.txt
mik_py.egg-info/top_level.txt