Metadata-Version: 2.1
Name: mik-py
Version: 0.0.2
Summary: A Python Package created to help test application security tools
Author: Mike
Author-email: michaelrchung@gmail.com
Classifier: Programming Language :: Python :: 3
Classifier: License :: OSI Approved :: MIT License
Classifier: Operating System :: OS Independent
Requires-Python: >=3.6
